riemann/__init__.py
riemann/blake2.py
riemann/blake256.py
riemann/py.typed
riemann/simple.py
riemann/utils.py
riemann/encoding/__init__.py
riemann/encoding/addresses.py
riemann/encoding/base58.py
riemann/encoding/bech32.py
riemann/encoding/cashaddr.py
riemann/networks/__init__.py
riemann/networks/networks.py
riemann/networks/standard.py
riemann/script/__init__.py
riemann/script/examples.py
riemann/script/opcodes.py
riemann/script/serialization.py
riemann/tests/__init__.py
riemann/tests/helpers.py
riemann/tests/test_blake256.py
riemann/tests/test_riemann.py
riemann/tests/test_simple.py
riemann/tests/test_utils.py
riemann/tests/encoding/__init__.py
riemann/tests/encoding/test_addresses.py
riemann/tests/encoding/test_base58.py
riemann/tests/encoding/test_bech32.py
riemann/tests/tx/__init__.py
riemann/tests/tx/overwinter_helpers.py
riemann/tests/tx/test_decred.py
riemann/tests/tx/test_overwinter.py
riemann/tests/tx/test_overwinter_sighash.py
riemann/tests/tx/test_sapling.py
riemann/tests/tx/test_shared.py
riemann/tests/tx/test_sprout.py
riemann/tests/tx/test_tx.py
riemann/tests/tx/test_tx_builder.py
riemann/tests/tx/helpers/__init__.py
riemann/tests/tx/helpers/decred_helpers.py
riemann/tests/tx/helpers/overwinter_helpers.py
riemann/tests/tx/helpers/sapling_helpers.py
riemann/tx/__init__.py
riemann/tx/decred.py
riemann/tx/overwinter.py
riemann/tx/sapling.py
riemann/tx/shared.py
riemann/tx/sprout.py
riemann/tx/tx.py
riemann/tx/tx_builder.py
riemann/tx/zcash_shared.py
riemann_tx-2.1.0.dist-info/LICENSE
riemann_tx-2.1.0.dist-info/METADATA
riemann_tx-2.1.0.dist-info/WHEEL
riemann_tx-2.1.0.dist-info/top_level.txt
riemann_tx-2.1.0.dist-info/RECORD
