Metadata-Version: 2.1
Name: riemann-tx
Version: 2.1.0
Summary: Transaction creation library for Bitcoin-like coins
Home-page: https://github.com/summa-tx/riemann
Author: James Prestwich
Author-email: james@summa.one
License: LICENSE
Keywords: bitcoin litecoin cryptocurrency decred blockchain development
Platform: UNKNOWN
Classifier: Programming Language :: Python
Classifier: Programming Language :: Python :: 3 :: Only
Classifier: Topic :: Security :: Cryptography
Classifier: Development Status :: 4 - Beta
Classifier: Intended Audience :: Developers
Classifier: License :: OSI Approved :: GNU Lesser General Public License v3 or later (LGPLv3+)
Classifier: Operating System :: OS Independent
Classifier: Topic :: Software Development :: Libraries :: Python Modules
Requires-Python: >=3.6
